aprsd_mqtt_plugin/__init__.py
aprsd_mqtt_plugin/aprsd_mqtt_plugin.py
aprsd_mqtt_plugin/conf/__init__.py
aprsd_mqtt_plugin/conf/main.py
aprsd_mqtt_plugin/conf/opts.py
aprsd_mqtt_plugin-0.2.0.dist-info/LICENSE
aprsd_mqtt_plugin-0.2.0.dist-info/METADATA
aprsd_mqtt_plugin-0.2.0.dist-info/WHEEL
aprsd_mqtt_plugin-0.2.0.dist-info/entry_points.txt
aprsd_mqtt_plugin-0.2.0.dist-info/pbr.json
aprsd_mqtt_plugin-0.2.0.dist-info/top_level.txt
aprsd_mqtt_plugin-0.2.0.dist-info/RECORD
